Workbook

Sheet Operaciones
A1: REGISTRO DE OPERACIONES | Spot & Futures
A2: # | B2: Fecha Entrada | C2: Fecha Cierre | D2: Tipo | E2: Activo | F2: Dirección | G2: Apalan- camiento | H2: Precio Entrada ($) | I2: Precio Cierre ($) | J2: Cantidad (monedas) | K2: Capital Invertido ($) | L2: Com. Entrada ($) | M2: Com. Cierre ($) | N2: Total Com. ($) | O2: PnL Bruto ($) | P2: PnL Neto ($) | Q2: PnL (%) | R2: Estado | S2: Exchange | T2: Notas
A3: =IF(B3<>"",ROW()-2,"") | K3: =IF(H3*J3=0,"",H3*J3) | N3: =IF(L3+M3=0,"",L3+M3) | O3: =IF(OR(H3="",I3="",J3=""),"",IF(F3="Long",(I3-H3)*J3*IF(G3="",1,G3),(H3-I3)*J3*IF(G3="",1,G3))) | P3: =IF(O3="","",O3-IF(N3="",0,N3)) | Q3: =IFERROR(IF(P3="","",P3/K3),"")
A4: =IF(B4<>"",ROW()-2,"") | K4: =IF(H4*J4=0,"",H4*J4) | N4: =IF(L4+M4=0,"",L4+M4) | O4: =IF(OR(H4="",I4="",J4=""),"",IF(F4="Long",(I4-H4)*J4*IF(G4="",1,G4),(H4-I4)*J4*IF(G4="",1,G4))) | P4: =IF(O4="","",O4-IF(N4="",0,N4)) | Q4: =IFERROR(IF(P4="","",P4/K4),"")
A5: =IF(B5<>"",ROW()-2,"") | K5: =IF(H5*J5=0,"",H5*J5) | N5: =IF(L5+M5=0,"",L5+M5) | O5: =IF(OR(H5="",I5="",J5=""),"",IF(F5="Long",(I5-H5)*J5*IF(G5="",1,G5),(H5-I5)*J5*IF(G5="",1,G5))) | P5: =IF(O5="","",O5-IF(N5="",0,N5)) | Q5: =IFERROR(IF(P5="","",P5/K5),"")
A6: =IF(B6<>"",ROW()-2,"") | K6: =IF(H6*J6=0,"",H6*J6) | N6: =IF(L6+M6=0,"",L6+M6) | O6: =IF(OR(H6="",I6="",J6=""),"",IF(F6="Long",(I6-H6)*J6*IF(G6="",1,G6),(H6-I6)*J6*IF(G6="",1,G6))) | P6: =IF(O6="","",O6-IF(N6="",0,N6)) | Q6: =IFERROR(IF(P6="","",P6/K6),"")
A7: =IF(B7<>"",ROW()-2,"") | K7: =IF(H7*J7=0,"",H7*J7) | N7: =IF(L7+M7=0,"",L7+M7) | O7: =IF(OR(H7="",I7="",J7=""),"",IF(F7="Long",(I7-H7)*J7*IF(G7="",1,G7),(H7-I7)*J7*IF(G7="",1,G7))) | P7: =IF(O7="","",O7-IF(N7="",0,N7)) | Q7: =IFERROR(IF(P7="","",P7/K7),"")
A8: =IF(B8<>"",ROW()-2,"") | K8: =IF(H8*J8=0,"",H8*J8) | N8: =IF(L8+M8=0,"",L8+M8) | O8: =IF(OR(H8="",I8="",J8=""),"",IF(F8="Long",(I8-H8)*J8*IF(G8="",1,G8),(H8-I8)*J8*IF(G8="",1,G8))) | P8: =IF(O8="","",O8-IF(N8="",0,N8)) | Q8: =IFERROR(IF(P8="","",P8/K8),"")
A9: =IF(B9<>"",ROW()-2,"") | K9: =IF(H9*J9=0,"",H9*J9) | N9: =IF(L9+M9=0,"",L9+M9) | O9: =IF(OR(H9="",I9="",J9=""),"",IF(F9="Long",(I9-H9)*J9*IF(G9="",1,G9),(H9-I9)*J9*IF(G9="",1,G9))) | P9: =IF(O9="","",O9-IF(N9="",0,N9)) | Q9: =IFERROR(IF(P9="","",P9/K9),"")
A10: =IF(B10<>"",ROW()-2,"") | K10: =IF(H10*J10=0,"",H10*J10) | N10: =IF(L10+M10=0,"",L10+M10) | O10: =IF(OR(H10="",I10="",J10=""),"",IF(F10="Long",(I10-H10)*J10*IF(G10="",1,G10),(H10-I10)*J10*IF(G10="",1,G10))) | P10: =IF(O10="","",O10-IF(N10="",0,N10)) | Q10: =IFERROR(IF(P10="","",P10/K10),"")
A11: =IF(B11<>"",ROW()-2,"") | K11: =IF(H11*J11=0,"",H11*J11) | N11: =IF(L11+M11=0,"",L11+M11) | O11: =IF(OR(H11="",I11="",J11=""),"",IF(F11="Long",(I11-H11)*J11*IF(G11="",1,G11),(H11-I11)*J11*IF(G11="",1,G11))) | P11: =IF(O11="","",O11-IF(N11="",0,N11)) | Q11: =IFERROR(IF(P11="","",P11/K11),"")
A12: =IF(B12<>"",ROW()-2,"") | K12: =IF(H12*J12=0,"",H12*J12) | N12: =IF(L12+M12=0,"",L12+M12) | O12: =IF(OR(H12="",I12="",J12=""),"",IF(F12="Long",(I12-H12)*J12*IF(G12="",1,G12),(H12-I12)*J12*IF(G12="",1,G12))) | P12: =IF(O12="","",O12-IF(N12="",0,N12)) | Q12: =IFERROR(IF(P12="","",P12/K12),"")
A13: =IF(B13<>"",ROW()-2,"") | K13: =IF(H13*J13=0,"",H13*J13) | N13: =IF(L13+M13=0,"",L13+M13) | O13: =IF(OR(H13="",I13="",J13=""),"",IF(F13="Long",(I13-H13)*J13*IF(G13="",1,G13),(H13-I13)*J13*IF(G13="",1,G13))) | P13: =IF(O13="","",O13-IF(N13="",0,N13)) | Q13: =IFERROR(IF(P13="","",P13/K13),"")
A14: =IF(B14<>"",ROW()-2,"") | K14: =IF(H14*J14=0,"",H14*J14) | N14: =IF(L14+M14=0,"",L14+M14) | O14: =IF(OR(H14="",I14="",J14=""),"",IF(F14="Long",(I14-H14)*J14*IF(G14="",1,G14),(H14-I14)*J14*IF(G14="",1,G14))) | P14: =IF(O14="","",O14-IF(N14="",0,N14)) | Q14: =IFERROR(IF(P14="","",P14/K14),"")
... A1002: =IF(B1002<>"",ROW()-2,"") | K1002: =IF(H1002*J1002=0,"",H1002*J1002) | N1002: =IF(L1002+M1002=0,"",L1002+M1002) | O1002: =IF(OR(H1002="",I1002="",J1002=""),"",IF(F1002="Long",(I1002-H1002)*J1002*IF(G1002="",1,G1002),(H1002-I1002)*J1002*IF(G1002="",1,G1002))) | P1002: =IF(O1002="","",O1002-IF(N1002="",0,N1002)) | Q1002: =IFERROR(IF(P1002="","",P1002/K1002),"")

Sheet Dashboard
A1: CRYPTO TRADING TRACKER | Dashboard de Rendimiento
A2: Indicadores actualizados automáticamente desde la hoja 'Operaciones'
A4: MÉTRICAS PRINCIPALES
B5: Total Operaciones | D5: Win Rate | F5: PnL Neto Total ($) | H5: Total Comisiones ($)
B6: =COUNTA(Operaciones!B3:B1002) -> 0 | D6: =IFERROR(COUNTIFS(Operaciones!R3:R1002,"Cerrada",Operaciones!P3:P1002,">0")/COUNTIF(Operaciones!R3:R1002,"Cerrada"),"-") -> - | F6: =IFERROR(SUM(Operaciones!P3:P1002),0) -> 0 | H6: =IFERROR(SUM(Operaciones!N3:N1002),0) -> 0
B9: Mejor Operación ($) | D9: Peor Operación ($) | F9: Retorno Promedio | H9: Ops. Abiertas
B10: =IFERROR(MAX(Operaciones!P3:P1002),0) -> 0 | D10: =IFERROR(MIN(Operaciones!P3:P1002),0) -> 0 | F10: =IFERROR(AVERAGEIF(Operaciones!R3:R1002,"Cerrada",Operaciones!Q3:Q1002),"-") -> - | H10: =COUNTIF(Operaciones!R3:R1002,"Abierta") -> 0
A14: ESTADÍSTICAS DETALLADAS
B15: Operaciones Spot | F15: =COUNTIF(Operaciones!D3:D1002,"Spot") -> 0
B16: Operaciones Futures | F16: =COUNTIF(Operaciones!D3:D1002,"Futures") -> 0
B17: Ops. Cerradas | F17: =COUNTIF(Operaciones!R3:R1002,"Cerrada") -> 0
B18: Trades Ganadores | F18: =COUNTIFS(Operaciones!R3:R1002,"Cerrada",Operaciones!P3:P1002,">0") -> 0
B19: Trades Perdedores | F19: =COUNTIFS(Operaciones!R3:R1002,"Cerrada",Operaciones!P3:P1002,"<0") -> 0
B20: Capital Total Invertido ($) | F20: =IFERROR(SUM(Operaciones!K3:K1002),0) -> 0
B21: PnL Prom. Ganador ($) | F21: =IFERROR(AVERAGEIFS(Operaciones!P3:P1002,Operaciones!R3:R1002,"Cerrada",Operaciones!P3:P1002,">0"),0) -> 0
B22: PnL Prom. Perdedor ($) | F22: =IFERROR(AVERAGEIFS(Operaciones!P3:P1002,Operaciones!R3:R1002,"Cerrada",Operaciones!P3:P1002,"<0"),0) -> 0
B23: Ratio Ganancia / Pérdida | F23: =IFERROR(ABS(AVERAGEIFS(Operaciones!P3:P1002,Operaciones!R3:R1002,"Cerrada",Operaciones!P3:P1002,">0"))/ABS(AVERAGEIFS(Operaciones!P3:P1002,Operaciones!R3:R1002,"Cerrada",Operaciones!P3:P1002,"<0")),"-") -> -
B24: Retorno Total (%) | F24: =IFERROR(SUM(Operaciones!P3:P1002)/SUM(Operaciones!K3:K1002),0) -> 0

Sheet Análisis por Activo
A1: ANÁLISIS DE RENDIMIENTO POR ACTIVO & TIPO
B3: RENDIMIENTO POR ACTIVO
B4: Activo | C4: # Trades | D4: PnL Neto ($) | E4: PnL Prom. ($) | F4: Win Rate | G4: Mejor Trade | H4: Peor Trade
B5: BTC | C5: =COUNTIF(Operaciones!E3:E1002,B5) -> 0 | D5: =IFERROR(SUMIF(Operaciones!E3:E1002,B5,Operaciones!P3:P1002),0) -> 0 | E5: =IFERROR(AVERAGEIF(Operaciones!E3:E1002,B5,Operaciones!P3:P1002),0) -> 0 | F5: =IFERROR(COUNTIFS(Operaciones!E3:E1002,B5,Operaciones!P3:P1002,">0")/C5,"-") -> - | G5: =IFERROR(maxifs(Operaciones!P3:P1002,Operaciones!E3:E1002,B5),0) -> 0 | H5: =IFERROR(minifs(Operaciones!P3:P1002,Operaciones!E3:E1002,B5),0) -> 0
B6: ETH | C6: =COUNTIF(Operaciones!E3:E1002,B6) -> 0 | D6: =IFERROR(SUMIF(Operaciones!E3:E1002,B6,Operaciones!P3:P1002),0) -> 0 | E6: =IFERROR(AVERAGEIF(Operaciones!E3:E1002,B6,Operaciones!P3:P1002),0) -> 0 | F6: =IFERROR(COUNTIFS(Operaciones!E3:E1002,B6,Operaciones!P3:P1002,">0")/C6,"-") -> - | G6: =IFERROR(maxifs(Operaciones!P3:P1002,Operaciones!E3:E1002,B6),0) -> 0 | H6: =IFERROR(minifs(Operaciones!P3:P1002,Operaciones!E3:E1002,B6),0) -> 0
B7: BNB | C7: =COUNTIF(Operaciones!E3:E1002,B7) -> 0 | D7: =IFERROR(SUMIF(Operaciones!E3:E1002,B7,Operaciones!P3:P1002),0) -> 0 | E7: =IFERROR(AVERAGEIF(Operaciones!E3:E1002,B7,Operaciones!P3:P1002),0) -> 0 | F7: =IFERROR(COUNTIFS(Operaciones!E3:E1002,B7,Operaciones!P3:P1002,">0")/C7,"-") -> - | G7: =IFERROR(maxifs(Operaciones!P3:P1002,Operaciones!E3:E1002,B7),0) -> 0 | H7: =IFERROR(minifs(Operaciones!P3:P1002,Operaciones!E3:E1002,B7),0) -> 0
B8: SOL | C8: =COUNTIF(Operaciones!E3:E1002,B8) -> 0 | D8: =IFERROR(SUMIF(Operaciones!E3:E1002,B8,Operaciones!P3:P1002),0) -> 0 | E8: =IFERROR(AVERAGEIF(Operaciones!E3:E1002,B8,Operaciones!P3:P1002),0) -> 0 | F8: =IFERROR(COUNTIFS(Operaciones!E3:E1002,B8,Operaciones!P3:P1002,">0")/C8,"-") -> - | G8: =IFERROR(maxifs(Operaciones!P3:P1002,Operaciones!E3:E1002,B8),0) -> 0 | H8: =IFERROR(minifs(Operaciones!P3:P1002,Operaciones!E3:E1002,B8),0) -> 0
B9: XRP | C9: =COUNTIF(Operaciones!E3:E1002,B9) -> 0 | D9: =IFERROR(SUMIF(Operaciones!E3:E1002,B9,Operaciones!P3:P1002),0) -> 0 | E9: =IFERROR(AVERAGEIF(Operaciones!E3:E1002,B9,Operaciones!P3:P1002),0) -> 0 | F9: =IFERROR(COUNTIFS(Operaciones!E3:E1002,B9,Operaciones!P3:P1002,">0")/C9,"-") -> - | G9: =IFERROR(maxifs(Operaciones!P3:P1002,Operaciones!E3:E1002,B9),0) -> 0 | H9: =IFERROR(minifs(Operaciones!P3:P1002,Operaciones!E3:E1002,B9),0) -> 0
B10: ADA | C10: =COUNTIF(Operaciones!E3:E1002,B10) -> 0 | D10: =IFERROR(SUMIF(Operaciones!E3:E1002,B10,Operaciones!P3:P1002),0) -> 0 | E10: =IFERROR(AVERAGEIF(Operaciones!E3:E1002,B10,Operaciones!P3:P1002),0) -> 0 | F10: =IFERROR(COUNTIFS(Operaciones!E3:E1002,B10,Operaciones!P3:P1002,">0")/C10,"-") -> - | G10: =IFERROR(maxifs(Operaciones!P3:P1002,Operaciones!E3:E1002,B10),0) -> 0 | H10: =IFERROR(minifs(Operaciones!P3:P1002,Operaciones!E3:E1002,B10),0) -> 0
B11: AVAX | C11: =COUNTIF(Operaciones!E3:E1002,B11) -> 0 | D11: =IFERROR(SUMIF(Operaciones!E3:E1002,B11,Operaciones!P3:P1002),0) -> 0 | E11: =IFERROR(AVERAGEIF(Operaciones!E3:E1002,B11,Operaciones!P3:P1002),0) -> 0 | F11: =IFERROR(COUNTIFS(Operaciones!E3:E1002,B11,Operaciones!P3:P1002,">0")/C11,"-") -> - | G11: =IFERROR(maxifs(Operaciones!P3:P1002,Operaciones!E3:E1002,B11),0) -> 0 | H11: =IFERROR(minifs(Operaciones!P3:P1002,Operaciones!E3:E1002,B11),0) -> 0
B12: DOGE | C12: =COUNTIF(Operaciones!E3:E1002,B12) -> 0 | D12: =IFERROR(SUMIF(Operaciones!E3:E1002,B12,Operaciones!P3:P1002),0) -> 0 | E12: =IFERROR(AVERAGEIF(Operaciones!E3:E1002,B12,Operaciones!P3:P1002),0) -> 0 | F12: =IFERROR(COUNTIFS(Operaciones!E3:E1002,B12,Operaciones!P3:P1002,">0")/C12,"-") -> - | G12: =IFERROR(maxifs(Operaciones!P3:P1002,Operaciones!E3:E1002,B12),0) -> 0 | H12: =IFERROR(minifs(Operaciones!P3:P1002,Operaciones!E3:E1002,B12),0) -> 0
B13: MATIC | C13: =COUNTIF(Operaciones!E3:E1002,B13) -> 0 | D13: =IFERROR(SUMIF(Operaciones!E3:E1002,B13,Operaciones!P3:P1002),0) -> 0 | E13: =IFERROR(AVERAGEIF(Operaciones!E3:E1002,B13,Operaciones!P3:P1002),0) -> 0 | F13: =IFERROR(COUNTIFS(Operaciones!E3:E1002,B13,Operaciones!P3:P1002,">0")/C13,"-") -> - | G13: =IFERROR(maxifs(Operaciones!P3:P1002,Operaciones!E3:E1002,B13),0) -> 0 | H13: =IFERROR(minifs(Operaciones!P3:P1002,Operaciones!E3:E1002,B13),0) -> 0
B14: DOT | C14: =COUNTIF(Operaciones!E3:E1002,B14) -> 0 | D14: =IFERROR(SUMIF(Operaciones!E3:E1002,B14,Operaciones!P3:P1002),0) -> 0 | E14: =IFERROR(AVERAGEIF(Operaciones!E3:E1002,B14,Operaciones!P3:P1002),0) -> 0 | F14: =IFERROR(COUNTIFS(Operaciones!E3:E1002,B14,Operaciones!P3:P1002,">0")/C14,"-") -> - | G14: =IFERROR(maxifs(Operaciones!P3:P1002,Operaciones!E3:E1002,B14),0) -> 0 | H14: =IFERROR(minifs(Operaciones!P3:P1002,Operaciones!E3:E1002,B14),0) -> 0
B15: Otro | C15: =COUNTIF(Operaciones!E3:E1002,B15) -> 0 | D15: =IFERROR(SUMIF(Operaciones!E3:E1002,B15,Operaciones!P3:P1002),0) -> 0 | E15: =IFERROR(AVERAGEIF(Operaciones!E3:E1002,B15,Operaciones!P3:P1002),0) -> 0 | F15: =IFERROR(COUNTIFS(Operaciones!E3:E1002,B15,Operaciones!P3:P1002,">0")/C15,"-") -> - | G15: =IFERROR(maxifs(Operaciones!P3:P1002,Operaciones!E3:E1002,B15),0) -> 0 | H15: =IFERROR(minifs(Operaciones!P3:P1002,Operaciones!E3:E1002,B15),0) -> 0
B19: RENDIMIENTO: SPOT vs FUTURES
B20: Tipo | C20: # Trades | D20: PnL Neto ($) | E20: PnL Prom. ($) | F20: Win Rate | G20: Mejor Trade | H20: Peor Trade
B21: Spot | C21: =COUNTIF(Operaciones!D3:D1002,B21) -> 0 | D21: =IFERROR(SUMIF(Operaciones!D3:D1002,B21,Operaciones!P3:P1002),0) -> 0 | E21: =IFERROR(AVERAGEIF(Operaciones!D3:D1002,B21,Operaciones!P3:P1002),0) -> 0 | F21: =IFERROR(COUNTIFS(Operaciones!D3:D1002,B21,Operaciones!P3:P1002,">0")/C21,"-") -> - | G21: =IFERROR(maxifs(Operaciones!P3:P1002,Operaciones!D3:D1002,B21),0) -> 0 | H21: =IFERROR(minifs(Operaciones!P3:P1002,Operaciones!D3:D1002,B21),0) -> 0
B22: Futures | C22: =COUNTIF(Operaciones!D3:D1002,B22) -> 0 | D22: =IFERROR(SUMIF(Operaciones!D3:D1002,B22,Operaciones!P3:P1002),0) -> 0 | E22: =IFERROR(AVERAGEIF(Operaciones!D3:D1002,B22,Operaciones!P3:P1002),0) -> 0 | F22: =IFERROR(COUNTIFS(Operaciones!D3:D1002,B22,Operaciones!P3:P1002,">0")/C22,"-") -> - | G22: =IFERROR(maxifs(Operaciones!P3:P1002,Operaciones!D3:D1002,B22),0) -> 0 | H22: =IFERROR(minifs(Operaciones!P3:P1002,Operaciones!D3:D1002,B22),0) -> 0
B25: RESUMEN MENSUAL (ingresa el mes en col. B para ver el PnL)
B26: Mes/Año | C26: # Trades | D26: PnL Neto ($) | E26: PnL Prom. ($) | F26: Win Rate | G26: Mejor Trade | H26: Peor Trade
C27: =IFERROR(SUMPRODUCT((MONTH(Operaciones!B3:B1002)=MONTH(B27))*(YEAR(Operaciones!B3:B1002)=YEAR(B27))*(Operaciones!B3:B1002<>"")),"-") -> 0 | D27: =IFERROR(SUMPRODUCT((MONTH(Operaciones!B3:B1002)=MONTH(B27))*(YEAR(Operaciones!B3:B1002)=YEAR(B27))*(Operaciones!B3:B1002<>"")*Operaciones!P3:P1002),"-") -> - | E27: =IFERROR(D27/C27,"-") -> - | F27: =IFERROR(SUMPRODUCT((MONTH(Operaciones!B3:B1002)=MONTH(B27))*(YEAR(Operaciones!B3:B1002)=YEAR(B27))*(Operaciones!P3:P1002>0)*(Operaciones!B3:B1002<>""))/C27,"-") -> - | G27: =IFERROR(maxifs(Operaciones!P3:P1002,Operaciones!B3:B1002,">="&DATE(YEAR(B27),MONTH(B27),1),Operaciones!B3:B1002,"<"&DATE(YEAR(B27),MONTH(B27)+1,1)),"-") -> - | H27: =IFERROR(minifs(Operaciones!P3:P1002,Operaciones!B3:B1002,">="&DATE(YEAR(B27),MONTH(B27),1),Operaciones!B3:B1002,"<"&DATE(YEAR(B27),MONTH(B27)+1,1)),"-") -> -
C28: =IFERROR(SUMPRODUCT((MONTH(Operaciones!B3:B1002)=MONTH(B28))*(YEAR(Operaciones!B3:B1002)=YEAR(B28))*(Operaciones!B3:B1002<>"")),"-") -> 0 | D28: =IFERROR(SUMPRODUCT((MONTH(Operaciones!B3:B1002)=MONTH(B28))*(YEAR(Operaciones!B3:B1002)=YEAR(B28))*(Operaciones!B3:B1002<>"")*Operaciones!P3:P1002),"-") -> - | E28: =IFERROR(D28/C28,"-") -> - | F28: =IFERROR(SUMPRODUCT((MONTH(Operaciones!B3:B1002)=MONTH(B28))*(YEAR(Operaciones!B3:B1002)=YEAR(B28))*(Operaciones!P3:P1002>0)*(Operaciones!B3:B1002<>""))/C28,"-") -> - | G28: =IFERROR(maxifs(Operaciones!P3:P1002,Operaciones!B3:B1002,">="&DATE(YEAR(B28),MONTH(B28),1),Operaciones!B3:B1002,"<"&DATE(YEAR(B28),MONTH(B28)+1,1)),"-") -> - | H28: =IFERROR(minifs(Operaciones!P3:P1002,Operaciones!B3:B1002,">="&DATE(YEAR(B28),MONTH(B28),1),Operaciones!B3:B1002,"<"&DATE(YEAR(B28),MONTH(B28)+1,1)),"-") -> -
C29: =IFERROR(SUMPRODUCT((MONTH(Operaciones!B3:B1002)=MONTH(B29))*(YEAR(Operaciones!B3:B1002)=YEAR(B29))*(Operaciones!B3:B1002<>"")),"-") -> 0 | D29: =IFERROR(SUMPRODUCT((MONTH(Operaciones!B3:B1002)=MONTH(B29))*(YEAR(Operaciones!B3:B1002)=YEAR(B29))*(Operaciones!B3:B1002<>"")*Operaciones!P3:P1002),"-") -> - | E29: =IFERROR(D29/C29,"-") -> - | F29: =IFERROR(SUMPRODUCT((MONTH(Operaciones!B3:B1002)=MONTH(B29))*(YEAR(Operaciones!B3:B1002)=YEAR(B29))*(Operaciones!P3:P1002>0)*(Operaciones!B3:B1002<>""))/C29,"-") -> - | G29: =IFERROR(maxifs(Operaciones!P3:P1002,Operaciones!B3:B1002,">="&DATE(YEAR(B29),MONTH(B29),1),Operaciones!B3:B1002,"<"&DATE(YEAR(B29),MONTH(B29)+1,1)),"-") -> - | H29: =IFERROR(minifs(Operaciones!P3:P1002,Operaciones!B3:B1002,">="&DATE(YEAR(B29),MONTH(B29),1),Operaciones!B3:B1002,"<"&DATE(YEAR(B29),MONTH(B29)+1,1)),"-") -> -
C30: =IFERROR(SUMPRODUCT((MONTH(Operaciones!B3:B1002)=MONTH(B30))*(YEAR(Operaciones!B3:B1002)=YEAR(B30))*(Operaciones!B3:B1002<>"")),"-") -> 0 | D30: =IFERROR(SUMPRODUCT((MONTH(Operaciones!B3:B1002)=MONTH(B30))*(YEAR(Operaciones!B3:B1002)=YEAR(B30))*(Operaciones!B3:B1002<>"")*Operaciones!P3:P1002),"-") -> - | E30: =IFERROR(D30/C30,"-") -> - | F30: =IFERROR(SUMPRODUCT((MONTH(Operaciones!B3:B1002)=MONTH(B30))*(YEAR(Operaciones!B3:B1002)=YEAR(B30))*(Operaciones!P3:P1002>0)*(Operaciones!B3:B1002<>""))/C30,"-") -> - | G30: =IFERROR(maxifs(Operaciones!P3:P1002,Operaciones!B3:B1002,">="&DATE(YEAR(B30),MONTH(B30),1),Operaciones!B3:B1002,"<"&DATE(YEAR(B30),MONTH(B30)+1,1)),"-") -> - | H30: =IFERROR(minifs(Operaciones!P3:P1002,Operaciones!B3:B1002,">="&DATE(YEAR(B30),MONTH(B30),1),Operaciones!B3:B1002,"<"&DATE(YEAR(B30),MONTH(B30)+1,1)),"-") -> -
C31: =IFERROR(SUMPRODUCT((MONTH(Operaciones!B3:B1002)=MONTH(B31))*(YEAR(Operaciones!B3:B1002)=YEAR(B31))*(Operaciones!B3:B1002<>"")),"-") -> 0 | D31: =IFERROR(SUMPRODUCT((MONTH(Operaciones!B3:B1002)=MONTH(B31))*(YEAR(Operaciones!B3:B1002)=YEAR(B31))*(Operaciones!B3:B1002<>"")*Operaciones!P3:P1002),"-") -> - | E31: =IFERROR(D31/C31,"-") -> - | F31: =IFERROR(SUMPRODUCT((MONTH(Operaciones!B3:B1002)=MONTH(B31))*(YEAR(Operaciones!B3:B1002)=YEAR(B31))*(Operaciones!P3:P1002>0)*(Operaciones!B3:B1002<>""))/C31,"-") -> - | G31: =IFERROR(maxifs(Operaciones!P3:P1002,Operaciones!B3:B1002,">="&DATE(YEAR(B31),MONTH(B31),1),Operaciones!B3:B1002,"<"&DATE(YEAR(B31),MONTH(B31)+1,1)),"-") -> - | H31: =IFERROR(minifs(Operaciones!P3:P1002,Operaciones!B3:B1002,">="&DATE(YEAR(B31),MONTH(B31),1),Operaciones!B3:B1002,"<"&DATE(YEAR(B31),MONTH(B31)+1,1)),"-") -> -
C32: =IFERROR(SUMPRODUCT((MONTH(Operaciones!B3:B1002)=MONTH(B32))*(YEAR(Operaciones!B3:B1002)=YEAR(B32))*(Operaciones!B3:B1002<>"")),"-") -> 0 | D32: =IFERROR(SUMPRODUCT((MONTH(Operaciones!B3:B1002)=MONTH(B32))*(YEAR(Operaciones!B3:B1002)=YEAR(B32))*(Operaciones!B3:B1002<>"")*Operaciones!P3:P1002),"-") -> - | E32: =IFERROR(D32/C32,"-") -> - | F32: =IFERROR(SUMPRODUCT((MONTH(Operaciones!B3:B1002)=MONTH(B32))*(YEAR(Operaciones!B3:B1002)=YEAR(B32))*(Operaciones!P3:P1002>0)*(Operaciones!B3:B1002<>""))/C32,"-") -> - | G32: =IFERROR(maxifs(Operaciones!P3:P1002,Operaciones!B3:B1002,">="&DATE(YEAR(B32),MONTH(B32),1),Operaciones!B3:B1002,"<"&DATE(YEAR(B32),MONTH(B32)+1,1)),"-") -> - | H32: =IFERROR(minifs(Operaciones!P3:P1002,Operaciones!B3:B1002,">="&DATE(YEAR(B32),MONTH(B32),1),Operaciones!B3:B1002,"<"&DATE(YEAR(B32),MONTH(B32)+1,1)),"-") -> -
C33: =IFERROR(SUMPRODUCT((MONTH(Operaciones!B3:B1002)=MONTH(B33))*(YEAR(Operaciones!B3:B1002)=YEAR(B33))*(Operaciones!B3:B1002<>"")),"-") -> 0 | D33: =IFERROR(SUMPRODUCT((MONTH(Operaciones!B3:B1002)=MONTH(B33))*(YEAR(Operaciones!B3:B1002)=YEAR(B33))*(Operaciones!B3:B1002<>"")*Operaciones!P3:P1002),"-") -> - | E33: =IFERROR(D33/C33,"-") -> - | F33: =IFERROR(SUMPRODUCT((MONTH(Operaciones!B3:B1002)=MONTH(B33))*(YEAR(Operaciones!B3:B1002)=YEAR(B33))*(Operaciones!P3:P1002>0)*(Operaciones!B3:B1002<>""))/C33,"-") -> - | G33: =IFERROR(maxifs(Operaciones!P3:P1002,Operaciones!B3:B1002,">="&DATE(YEAR(B33),MONTH(B33),1),Operaciones!B3:B1002,"<"&DATE(YEAR(B33),MONTH(B33)+1,1)),"-") -> - | H33: =IFERROR(minifs(Operaciones!P3:P1002,Operaciones!B3:B1002,">="&DATE(YEAR(B33),MONTH(B33),1),Operaciones!B3:B1002,"<"&DATE(YEAR(B33),MONTH(B33)+1,1)),"-") -> -
C34: =IFERROR(SUMPRODUCT((MONTH(Operaciones!B3:B1002)=MONTH(B34))*(YEAR(Operaciones!B3:B1002)=YEAR(B34))*(Operaciones!B3:B1002<>"")),"-") -> 0 | D34: =IFERROR(SUMPRODUCT((MONTH(Operaciones!B3:B1002)=MONTH(B34))*(YEAR(Operaciones!B3:B1002)=YEAR(B34))*(Operaciones!B3:B1002<>"")*Operaciones!P3:P1002),"-") -> - | E34: =IFERROR(D34/C34,"-") -> - | F34: =IFERROR(SUMPRODUCT((MONTH(Operaciones!B3:B1002)=MONTH(B34))*(YEAR(Operaciones!B3:B1002)=YEAR(B34))*(Operaciones!P3:P1002>0)*(Operaciones!B3:B1002<>""))/C34,"-") -> - | G34: =IFERROR(maxifs(Operaciones!P3:P1002,Operaciones!B3:B1002,">="&DATE(YEAR(B34),MONTH(B34),1),Operaciones!B3:B1002,"<"&DATE(YEAR(B34),MONTH(B34)+1,1)),"-") -> - | H34: =IFERROR(minifs(Operaciones!P3:P1002,Operaciones!B3:B1002,">="&DATE(YEAR(B34),MONTH(B34),1),Operaciones!B3:B1002,"<"&DATE(YEAR(B34),MONTH(B34)+1,1)),"-") -> -
C35: =IFERROR(SUMPRODUCT((MONTH(Operaciones!B3:B1002)=MONTH(B35))*(YEAR(Operaciones!B3:B1002)=YEAR(B35))*(Operaciones!B3:B1002<>"")),"-") -> 0 | D35: =IFERROR(SUMPRODUCT((MONTH(Operaciones!B3:B1002)=MONTH(B35))*(YEAR(Operaciones!B3:B1002)=YEAR(B35))*(Operaciones!B3:B1002<>"")*Operaciones!P3:P1002),"-") -> - | E35: =IFERROR(D35/C35,"-") -> - | F35: =IFERROR(SUMPRODUCT((MONTH(Operaciones!B3:B1002)=MONTH(B35))*(YEAR(Operaciones!B3:B1002)=YEAR(B35))*(Operaciones!P3:P1002>0)*(Operaciones!B3:B1002<>""))/C35,"-") -> - | G35: =IFERROR(maxifs(Operaciones!P3:P1002,Operaciones!B3:B1002,">="&DATE(YEAR(B35),MONTH(B35),1),Operaciones!B3:B1002,"<"&DATE(YEAR(B35),MONTH(B35)+1,1)),"-") -> - | H35: =IFERROR(minifs(Operaciones!P3:P1002,Operaciones!B3:B1002,">="&DATE(YEAR(B35),MONTH(B35),1),Operaciones!B3:B1002,"<"&DATE(YEAR(B35),MONTH(B35)+1,1)),"-") -> -
C36: =IFERROR(SUMPRODUCT((MONTH(Operaciones!B3:B1002)=MONTH(B36))*(YEAR(Operaciones!B3:B1002)=YEAR(B36))*(Operaciones!B3:B1002<>"")),"-") -> 0 | D36: =IFERROR(SUMPRODUCT((MONTH(Operaciones!B3:B1002)=MONTH(B36))*(YEAR(Operaciones!B3:B1002)=YEAR(B36))*(Operaciones!B3:B1002<>"")*Operaciones!P3:P1002),"-") -> - | E36: =IFERROR(D36/C36,"-") -> - | F36: =IFERROR(SUMPRODUCT((MONTH(Operaciones!B3:B1002)=MONTH(B36))*(YEAR(Operaciones!B3:B1002)=YEAR(B36))*(Operaciones!P3:P1002>0)*(Operaciones!B3:B1002<>""))/C36,"-") -> - | G36: =IFERROR(maxifs(Operaciones!P3:P1002,Operaciones!B3:B1002,">="&DATE(YEAR(B36),MONTH(B36),1),Operaciones!B3:B1002,"<"&DATE(YEAR(B36),MONTH(B36)+1,1)),"-") -> - | H36: =IFERROR(minifs(Operaciones!P3:P1002,Operaciones!B3:B1002,">="&DATE(YEAR(B36),MONTH(B36),1),Operaciones!B3:B1002,"<"&DATE(YEAR(B36),MONTH(B36)+1,1)),"-") -> -
C37: =IFERROR(SUMPRODUCT((MONTH(Operaciones!B3:B1002)=MONTH(B37))*(YEAR(Operaciones!B3:B1002)=YEAR(B37))*(Operaciones!B3:B1002<>"")),"-") -> 0 | D37: =IFERROR(SUMPRODUCT((MONTH(Operaciones!B3:B1002)=MONTH(B37))*(YEAR(Operaciones!B3:B1002)=YEAR(B37))*(Operaciones!B3:B1002<>"")*Operaciones!P3:P1002),"-") -> - | E37: =IFERROR(D37/C37,"-") -> - | F37: =IFERROR(SUMPRODUCT((MONTH(Operaciones!B3:B1002)=MONTH(B37))*(YEAR(Operaciones!B3:B1002)=YEAR(B37))*(Operaciones!P3:P1002>0)*(Operaciones!B3:B1002<>""))/C37,"-") -> - | G37: =IFERROR(maxifs(Operaciones!P3:P1002,Operaciones!B3:B1002,">="&DATE(YEAR(B37),MONTH(B37),1),Operaciones!B3:B1002,"<"&DATE(YEAR(B37),MONTH(B37)+1,1)),"-") -> - | H37: =IFERROR(minifs(Operaciones!P3:P1002,Operaciones!B3:B1002,">="&DATE(YEAR(B37),MONTH(B37),1),Operaciones!B3:B1002,"<"&DATE(YEAR(B37),MONTH(B37)+1,1)),"-") -> -
C38: =IFERROR(SUMPRODUCT((MONTH(Operaciones!B3:B1002)=MONTH(B38))*(YEAR(Operaciones!B3:B1002)=YEAR(B38))*(Operaciones!B3:B1002<>"")),"-") -> 0 | D38: =IFERROR(SUMPRODUCT((MONTH(Operaciones!B3:B1002)=MONTH(B38))*(YEAR(Operaciones!B3:B1002)=YEAR(B38))*(Operaciones!B3:B1002<>"")*Operaciones!P3:P1002),"-") -> - | E38: =IFERROR(D38/C38,"-") -> - | F38: =IFERROR(SUMPRODUCT((MONTH(Operaciones!B3:B1002)=MONTH(B38))*(YEAR(Operaciones!B3:B1002)=YEAR(B38))*(Operaciones!P3:P1002>0)*(Operaciones!B3:B1002<>""))/C38,"-") -> - | G38: =IFERROR(maxifs(Operaciones!P3:P1002,Operaciones!B3:B1002,">="&DATE(YEAR(B38),MONTH(B38),1),Operaciones!B3:B1002,"<"&DATE(YEAR(B38),MONTH(B38)+1,1)),"-") -> - | H38: =IFERROR(minifs(Operaciones!P3:P1002,Operaciones!B3:B1002,">="&DATE(YEAR(B38),MONTH(B38),1),Operaciones!B3:B1002,"<"&DATE(YEAR(B38),MONTH(B38)+1,1)),"-") -> -

Sheet Instrucciones
A1: GUÍA DE USO — CRYPTO TRADING TRACKER
B3: CÓMO USAR ESTE ARCHIVO
B4: 1. Ve a la hoja 'Operaciones' para registrar cada trade.
B5: 2. Completa los campos en AZUL — son los únicos que debes editar.
B6: 3. Los campos en NEGRO se calculan automáticamente (no editar).
B7: 4. El Dashboard se actualiza solo con cada operación ingresada.
B8: 5. En 'Análisis por Activo': ingresa fechas (formato fecha) en col. B de Resumen Mensual.
B10: CAMPOS DE LA HOJA OPERACIONES
B11: • Fecha Entrada / Fecha Cierre
B12: • Tipo
B13: • Activo
B14: • Dirección
B15: • Apalancamiento
... B30: Fondo ÁMBAR
